stub/__init__.py
stub/stub.py
pybites_stub-0.1.dist-info/WHEEL
pybites_stub-0.1.dist-info/METADATA
pybites_stub-0.1.dist-info/RECORD
